pybman/__init__.py
pybman/client.py
pybman/data.py
pybman/extract.py
pybman/inspector.py
pybman/local.py
pybman/query.py
pybman/rest.py
pybman/utils.py
pybman/static/elastic/item-all-files-released.json
pybman/static/elastic/item-all-locators-released.json
pybman/static/elastic/item-ctx-released.json
pybman/static/elastic/item-ctx.json
pybman/static/elastic/item-jour-released.json
pybman/static/elastic/item-jour.json
pybman/static/elastic/item-lang-released.json
pybman/static/elastic/item-lang.json
pybman/static/elastic/item-ou-released.json
pybman/static/elastic/item-ou.json
pybman/static/elastic/item-pers-released.json
pybman/static/elastic/item-pers.json
pybman-2019.10.17.dist-info/COPYING
pybman-2019.10.17.dist-info/METADATA
pybman-2019.10.17.dist-info/WHEEL
pybman-2019.10.17.dist-info/top_level.txt
pybman-2019.10.17.dist-info/RECORD
