Metadata-Version: 2.1
Name: pybman
Version: 2019.10.17
Summary: Python package for interacting with MPG.PuRe
Home-page: https://github.com/herreio/pybman/
Author: Donatus Herre
Author-email: pypi@herre.io
License: GPL
Platform: UNKNOWN
Classifier: Development Status :: 2 - Pre-Alpha
Classifier: Intended Audience :: Science/Research
Classifier: Intended Audience :: Developers
Classifier: Programming Language :: Python
Classifier: Programming Language :: Python :: 3
Classifier: Operating System :: OS Independent
Classifier: License :: OSI Approved :: GNU General Public License v3 (GPLv3)
Requires-Dist: certifi (==2019.9.11)
Requires-Dist: chardet (==3.0.4)
Requires-Dist: idna (==2.8)
Requires-Dist: requests (==2.22.0)
Requires-Dist: tqdm (==4.36.1)
Requires-Dist: urllib3 (==1.25.6)
